compiledb/__init__.py
compiledb/__main__.py
compiledb/cli.py
compiledb/compiler.py
compiledb/parser.py
compiledb/utils.py
compiledb/commands/__init__.py
compiledb/commands/make.py
compiledb-0.10.6.dist-info/licenses/LICENSE
compiledb-0.10.6.dist-info/METADATA
compiledb-0.10.6.dist-info/WHEEL
compiledb-0.10.6.dist-info/entry_points.txt
compiledb-0.10.6.dist-info/top_level.txt
compiledb-0.10.6.dist-info/RECORD
