Metadata-Version: 2.4
Name: compiledb
Version: 0.10.6
Summary: Tool for generating Clang JSON Compilation Database files for make-based build systems.
Author-email: Nick Yamane <nickdiego@igalia.com>
License: GPL-3.0-or-later
Project-URL: Repository, https://github.com/nickdiego/compiledb.git
Project-URL: Issues, https://github.com/nickdiego/compiledb/issues
Keywords: compilation-database,clang,c,cpp,makefile,make,language-server,lsp
Classifier: Development Status :: 4 - Beta
Classifier: Intended Audience :: Developers
Classifier: Topic :: Software Development :: Build Tools
Classifier: License :: OSI Approved :: GNU General Public License v3 (GPLv3)
Classifier: Programming Language :: Python :: 2
Classifier: Programming Language :: Python :: 2.7
Classifier: Programming Language :: Python :: 3
Classifier: Programming Language :: Python :: 3.6
Classifier: Operating System :: OS Independent
Requires-Python: >=3.3
License-File: LICENSE
Requires-Dist: click
Requires-Dist: bashlex
Provides-Extra: dev
Requires-Dist: pytest; extra == "dev"
Requires-Dist: coverage; extra == "dev"
Requires-Dist: pytest-cov; extra == "dev"
Requires-Dist: pycodestyle; extra == "dev"
Requires-Dist: flake8; extra == "dev"
Requires-Dist: tox; extra == "dev"
Dynamic: license-file
